emoji/__init__.py
emoji/core.py
emoji/py.typed
emoji/tokenizer.py
emoji/unicode_codes/__init__.py
emoji/unicode_codes/data_dict.py
emoji/unicode_codes/emoji.json
emoji/unicode_codes/emoji_ar.json
emoji/unicode_codes/emoji_de.json
emoji/unicode_codes/emoji_es.json
emoji/unicode_codes/emoji_fa.json
emoji/unicode_codes/emoji_fr.json
emoji/unicode_codes/emoji_id.json
emoji/unicode_codes/emoji_it.json
emoji/unicode_codes/emoji_ja.json
emoji/unicode_codes/emoji_ko.json
emoji/unicode_codes/emoji_pt.json
emoji/unicode_codes/emoji_ru.json
emoji/unicode_codes/emoji_tr.json
emoji/unicode_codes/emoji_zh.json
emoji-2.13.2.dist-info/LICENSE.txt
emoji-2.13.2.dist-info/METADATA
emoji-2.13.2.dist-info/WHEEL
emoji-2.13.2.dist-info/top_level.txt
emoji-2.13.2.dist-info/RECORD
